{
    "id": "headsman",
    "name": "Headsman",
    "factions": ["isa"],
    "type": "warjack",
    "expansion": "tw",
    "subtypes": ["champion"],
    "cadre": "alliance_regulators",
    "stats": {
        "dc": 4,
        "base_size": 50,
        "spd": 5,
        "str": 5,
        "mat": 4,
        "rat": 4,
        "def": 3,
        "arm": 4,
        "boxes": 4
    },
    "weapons": [
        "eye_of_sorrows",
        "tractor_cannon",
        "heavy_fusion_blade"
    ],
    "advantages": [
        "revelator"
    ],
    "special_rules": [
        "dominion_converter",
        "thrusters"
    ]
}